MANIFEST.in
setup.py
gdrive_manager/__init__.py
gdrive_manager/client_secret.json
gdrive_manager/gdrive_manager.py
gdrive_manager.egg-info/PKG-INFO
gdrive_manager.egg-info/SOURCES.txt
gdrive_manager.egg-info/dependency_links.txt
gdrive_manager.egg-info/entry_points.txt
gdrive_manager.egg-info/requires.txt
gdrive_manager.egg-info/top_level.txt