Metadata-Version: 1.0
Name: gdrive-manager
Version: 0.1.10
Summary: Download / upload data using Google Drive APIs.
Home-page: https://github.com/nlbao/gdrive-manager
Author: Bao Nguyen
Author-email: nlbao95@gmail.com
License: MIT
Platform: UNKNOWN
